{
	"highlight": true,
	"title": {
		"en": "Turn off climatisation",
		"nl": "Klimaatregeling uitzetten",
		"de": "Klimatisierung ausschalten",
		"fr": "Désactiver la climatisation",
		"es": "Apagar climatización",
		"it": "Spegni climatizzazione",
		"da": "Sluk klimaanlæg",
		"no": "Slå av klimaanlegg",
		"sv": "Slå av klimatanläggning",
		"pl": "Wyłącz klimatyzację",
		"ru": "Выключить климатизацию",
		"ko": "냉난방 끄기"
	},
	"args": [
		{
			"type": "device",
			"name": "device",
			"filter": "driver_id=volkswagen|skoda&capabilities=climatisation_onoff"
		}
	]
}
